{"_type":"export","__export_format":4,"__export_date":"2021-07-13T18:48:31.498Z","__export_source":"insomnia.desktop.app:v2021.4.1","resources":[{"_id":"req_1fd1390c9e134153b11b97afd42b2374","parentId":"fld_c8a40052779c478fb1e0c901f854d51b","modified":1626117702378,"created":1626117634584,"url":"{{ _.base_url }}","name":"Index","description":"","method":"GET","body":{},"parameters":[],"headers":[],"authentication":{},"metaSortKey":-1626117634584,"isPrivate":false,"settingStoreCookies":true,"settingSendCookies":true,"settingDisableRenderRequestBody":false,"settingEncodeUrl":true,"settingRebuildPath":true,"settingFollowRedirects":"global","_type":"request"},{"_id":"fld_c8a40052779c478fb1e0c901f854d51b","parentId":"wrk_ed834b3db067417aba2f5551794065f8","modified":1626117589406,"created":1626117589406,"name":"Home","description":"","environment":{},"environmentPropertyOrder":null,"metaSortKey":-1626117589406,"_type":"request_group"},{"_id":"wrk_ed834b3db067417aba2f5551794065f8","parentId":null,"modified":1626117520259,"created":1626112471139,"name":"Escola","description":"","scope":"collection","_type":"workspace"},{"_id":"req_cc509c9d602a455591cfa48c10459ac9","parentId":"fld_14e779ed25b24a3ba75a3e0c690b9748","modified":1626197417098,"created":1626195109157,"url":"{{ _.base_url }}/users/","name":"Store","description":"","method":"POST","body":{"mimeType":"application/json","text":"{\n\t\"nome\": \"ciriguela\",\n\t\"password\": \"a1s2d3f4\",\n\t\"email\": \"teste@mail.com\"\n}"},"parameters":[],"headers":[{"name":"Content-Type","value":"application/json","id":"pair_1444d8a14bbf4b98a6582c91433fa171"}],"authentication":{},"metaSortKey":-1626195109157,"isPrivate":false,"settingStoreCookies":true,"settingSendCookies":true,"settingDisableRenderRequestBody":false,"settingEncodeUrl":true,"settingRebuildPath":true,"settingFollowRedirects":"global","_type":"request"},{"_id":"fld_14e779ed25b24a3ba75a3e0c690b9748","parentId":"wrk_ed834b3db067417aba2f5551794065f8","modified":1626195095977,"created":1626195095977,"name":"Users","description":"","environment":{},"environmentPropertyOrder":null,"metaSortKey":-1626195095977,"_type":"request_group"},{"_id":"req_3c859edc69104f0fa1b8c58c627a912c","parentId":"fld_14e779ed25b24a3ba75a3e0c690b9748","modified":1626198014412,"created":1626198004990,"url":"{{ _.base_url }}/users/","name":"Index","description":"","method":"GET","body":{},"parameters":[],"headers":[],"authentication":{},"metaSortKey":-1626198004990,"isPrivate":false,"settingStoreCookies":true,"settingSendCookies":true,"settingDisableRenderRequestBody":false,"settingEncodeUrl":true,"settingRebuildPath":true,"settingFollowRedirects":"global","_type":"request"},{"_id":"req_3c69d8050555408296581b874f9281d8","parentId":"fld_14e779ed25b24a3ba75a3e0c690b9748","modified":1626198290282,"created":1626198280986,"url":"{{ _.base_url }}/users/","name":"Show","description":"","method":"GET","body":{},"parameters":[],"headers":[],"authentication":{},"metaSortKey":-1626198280986,"isPrivate":false,"settingStoreCookies":true,"settingSendCookies":true,"settingDisableRenderRequestBody":false,"settingEncodeUrl":true,"settingRebuildPath":true,"settingFollowRedirects":"global","_type":"request"},{"_id":"req_53a2e4e65830456bbc410a0ba7de42b2","parentId":"fld_14e779ed25b24a3ba75a3e0c690b9748","modified":1626198798822,"created":1626198768302,"url":"{{ _.base_url }}/users/1","name":"Update","description":"","method":"PUT","body":{"mimeType":"application/json","text":""},"parameters":[],"headers":[{"name":"Content-Type","value":"application/json"}],"authentication":{},"metaSortKey":-1626198768302,"isPrivate":false,"settingStoreCookies":true,"settingSendCookies":true,"settingDisableRenderRequestBody":false,"settingEncodeUrl":true,"settingRebuildPath":true,"settingFollowRedirects":"global","_type":"request"},{"_id":"req_f2fda193150349f08c52c3c3d20b1709","parentId":"fld_14e779ed25b24a3ba75a3e0c690b9748","modified":1626199768900,"created":1626199743003,"url":"{{ _.base_url }}/users/1","name":"Delete","description":"","method":"DELETE","body":{},"parameters":[],"headers":[],"authentication":{},"metaSortKey":-1626199743003,"isPrivate":false,"settingStoreCookies":true,"settingSendCookies":true,"settingDisableRenderRequestBody":false,"settingEncodeUrl":true,"settingRebuildPath":true,"settingFollowRedirects":"global","_type":"request"},{"_id":"env_24be5c12ce4006e2a3b6cdb3a85d86376f1e12c0","parentId":"wrk_ed834b3db067417aba2f5551794065f8","modified":1626177118275,"created":1626112471172,"name":"Base Environment","data":{"base_url":"http://localhost:3001"},"dataPropertyOrder":{"&":["base_url"]},"color":null,"isPrivate":false,"metaSortKey":1626112471172,"_type":"environment"},{"_id":"jar_24be5c12ce4006e2a3b6cdb3a85d86376f1e12c0","parentId":"wrk_ed834b3db067417aba2f5551794065f8","modified":1626112471174,"created":1626112471174,"name":"Default Jar","cookies":[],"_type":"cookie_jar"},{"_id":"spc_ba25a639245e4e2db760221854a07e54","parentId":"wrk_ed834b3db067417aba2f5551794065f8","modified":1626112471140,"created":1626112471140,"fileName":"Insomnia","contents":"","contentType":"yaml","_type":"api_spec"}]}